confluence/__init__.py
confluence/__main__.py
confluence/__version__.py
confluence/attachment/__init__.py
confluence/attachment/create_attachment.py
confluence/attachment/delete_attachment.py
confluence/attachment/get_attachment.py
confluence/attachment/subcommand.py
confluence/common/__init__.py
confluence/common/api.py
confluence/common/cli.py
confluence/common/utils.py
confluence/content/__init__.py
confluence/content/get_content_by_id.py
confluence/content/subcommand.py
confluence/data/logging.yaml
confluence/local/__init__.py
confluence/local/convert_html_to_xml.py
confluence/local/subcommand.py
confluence/page/__init__.py
confluence/page/get_page_body.py
confluence/page/subcommand.py
confluence/page/update_page.py
confluence/py.typed
kci_confluence_cli-0.3.0.dist-info/METADATA
kci_confluence_cli-0.3.0.dist-info/WHEEL
kci_confluence_cli-0.3.0.dist-info/entry_points.txt
kci_confluence_cli-0.3.0.dist-info/RECORD
