Metadata-Version: 2.1
Name: kci-confluence-cli
Version: 0.3.0
Summary: 来栖川電算が利用しているConfluence v6.15.7を操作するためのCLIです。
Home-page: https://github.com/kurusugawa-computer/confluence-cli
License: MIT
Author: Kurusugawa Computer Inc.
Requires-Python: >=3.9,<4.0
Classifier: Development Status :: 4 - Beta
Classifier: Environment :: Console
Classifier: Intended Audience :: Developers
Classifier: License :: OSI Approved :: MIT License
Classifier: Operating System :: OS Independent
Classifier: Programming Language :: Python :: 3
Classifier: Programming Language :: Python :: 3.9
Classifier: Programming Language :: Python :: 3.10
Classifier: Programming Language :: Python :: 3.11
Classifier: Programming Language :: Python :: 3.12
Classifier: Topic :: Utilities
Requires-Dist: backoff
Requires-Dist: more_itertools
Requires-Dist: pyquery (>=2,<3)
Requires-Dist: pyyaml
Requires-Dist: requests
Requires-Dist: requests-toolbelt (>=1,<2)
Project-URL: Repository, https://github.com/kurusugawa-computer/confluence-cli
